amsterdam_django_oidc/__init__.py
amsterdam_django_oidc/py.typed
amsterdam_django_oidc-0.2.3.dist-info/WHEEL
amsterdam_django_oidc-0.2.3.dist-info/METADATA
amsterdam_django_oidc-0.2.3.dist-info/RECORD
