Metadata-Version: 2.3
Name: amsterdam-django-oidc
Version: 0.2.3
Summary: Extension of the authenctication backend of the mozilla-django-oidc package, with extra validation.
Author: Nino van der Laan, Youri Westerman
Author-email: Nino van der Laan <n.van.der.laan@amsterdam.nl>, Youri Westerman <y.westerman@amsterdam.nl>
Requires-Dist: mozilla-django-oidc>=5.0.2,<6.0.0
Requires-Python: >=3.10, <4.0
Project-URL: Repository, http://github.com/Amsterdam/amsterdam-django-oidc.git
